csp_advanced/__init__.py
csp_advanced/admin.py
csp_advanced/apps.py
csp_advanced/csp.py
csp_advanced/middleware.py
csp_advanced/models.py
csp_advanced/tests.py
csp_advanced/utils.py
csp_advanced/views.py
csp_advanced/migrations/__init__.py
django_csp_advanced-0.1.0.dist-info/METADATA
django_csp_advanced-0.1.0.dist-info/WHEEL
django_csp_advanced-0.1.0.dist-info/top_level.txt
django_csp_advanced-0.1.0.dist-info/RECORD
